monistode_linker/__init__.py
monistode_linker/cli.py
monistode_linker/linker.py
monistode_linker-0.1.8.dist-info/METADATA
monistode_linker-0.1.8.dist-info/WHEEL
monistode_linker-0.1.8.dist-info/entry_points.txt
monistode_linker-0.1.8.dist-info/RECORD
